llamafactory/__init__.py
llamafactory/cli.py
llamafactory/launcher.py
llamafactory/api/__init__.py
llamafactory/api/app.py
llamafactory/api/chat.py
llamafactory/api/common.py
llamafactory/api/protocol.py
llamafactory/chat/__init__.py
llamafactory/chat/base_engine.py
llamafactory/chat/chat_model.py
llamafactory/chat/hf_engine.py
llamafactory/chat/sglang_engine.py
llamafactory/chat/vllm_engine.py
llamafactory/data/__init__.py
llamafactory/data/collator.py
llamafactory/data/converter.py
llamafactory/data/data_utils.py
llamafactory/data/formatter.py
llamafactory/data/loader.py
llamafactory/data/mm_plugin.py
llamafactory/data/parser.py
llamafactory/data/template.py
llamafactory/data/tool_utils.py
llamafactory/data/processor/__init__.py
llamafactory/data/processor/feedback.py
llamafactory/data/processor/pairwise.py
llamafactory/data/processor/pretrain.py
llamafactory/data/processor/processor_utils.py
llamafactory/data/processor/supervised.py
llamafactory/data/processor/unsupervised.py
llamafactory/eval/__init__.py
llamafactory/eval/evaluator.py
llamafactory/eval/template.py
llamafactory/extras/__init__.py
llamafactory/extras/constants.py
llamafactory/extras/env.py
llamafactory/extras/logging.py
llamafactory/extras/misc.py
llamafactory/extras/packages.py
llamafactory/extras/ploting.py
llamafactory/hparams/__init__.py
llamafactory/hparams/data_args.py
llamafactory/hparams/evaluation_args.py
llamafactory/hparams/finetuning_args.py
llamafactory/hparams/generating_args.py
llamafactory/hparams/model_args.py
llamafactory/hparams/parser.py
llamafactory/hparams/training_args.py
llamafactory/model/__init__.py
llamafactory/model/adapter.py
llamafactory/model/loader.py
llamafactory/model/patcher.py
llamafactory/model/model_utils/__init__.py
llamafactory/model/model_utils/attention.py
llamafactory/model/model_utils/checkpointing.py
llamafactory/model/model_utils/embedding.py
llamafactory/model/model_utils/kv_cache.py
llamafactory/model/model_utils/liger_kernel.py
llamafactory-0.9.3.dist-info/licenses/LICENSE
llamafactory-0.9.3.dist-info/METADATA
llamafactory-0.9.3.dist-info/WHEEL
llamafactory-0.9.3.dist-info/entry_points.txt
llamafactory-0.9.3.dist-info/top_level.txt
llamafactory-0.9.3.dist-info/RECORD
